apple_ocr/__init__.py
apple_ocr/ocr.py
apple_ocr-1.0.8.dist-info/LICENSE
apple_ocr-1.0.8.dist-info/METADATA
apple_ocr-1.0.8.dist-info/WHEEL
apple_ocr-1.0.8.dist-info/top_level.txt
apple_ocr-1.0.8.dist-info/RECORD
