Metadata-Version: 2.1
Name: apple-ocr
Version: 1.0.8
Summary: An OCR (Optical Character Recognition) utility for text extraction from images.
Keywords: OCR,image-recognition,text-extraction,clustering,Apple Vision,NLP,LLM,data
Classifier: Programming Language :: Python
Classifier: Programming Language :: Python :: 3
Classifier: Intended Audience :: Education
Classifier: Intended Audience :: Science/Research
Classifier: License :: OSI Approved :: Apache Software License
Classifier: Topic :: Scientific/Engineering
Classifier: Topic :: Scientific/Engineering :: Artificial Intelligence
Classifier: Topic :: Software Development
Classifier: Topic :: Software Development :: Libraries
Classifier: Topic :: Software Development :: Libraries :: Python Modules
License-File: LICENSE
